[{"tipo":"LOGIN_FAIL","ip":"::ffff:170.155.150.154","endpoint":"/api/login","detalle":"Usuario: \"baccegam\"","ts":"2026-03-26T16:03:46.103Z"},{"tipo":"LOGIN_FAIL","ip":"::ffff:170.155.150.154","endpoint":"/api/login","detalle":"Usuario: \"baccegam\"","ts":"2026-03-26T16:03:40.800Z"},{"tipo":"PRIMER_LOGIN_COMPLETADO","ip":"::ffff:181.23.113.245","endpoint":"/api/inspector/primer-cambio-password","detalle":"Usuario: sarmientoa","ts":"2026-03-26T03:14:52.587Z"},{"tipo":"LOGIN_FAIL","ip":"::ffff:181.23.113.245","endpoint":"/api/login","detalle":"Usuario: \"sarmientoa\"","ts":"2026-03-26T03:14:35.290Z"},{"tipo":"LOGIN_FAIL","ip":"::ffff:181.23.113.245","endpoint":"/api/login","detalle":"Usuario: \"sarmientoa\"","ts":"2026-03-26T03:14:29.426Z"},{"tipo":"LOGIN_FAIL","ip":"::ffff:181.23.113.245","endpoint":"/api/login","detalle":"Usuario: \"sarmientoa\"","ts":"2026-03-26T03:14:22.858Z"},{"tipo":"LOGIN_FAIL","ip":"::ffff:181.23.113.245","endpoint":"/api/login","detalle":"Usuario: \"amatof\"","ts":"2026-03-26T03:12:53.297Z"},{"tipo":"BACKUP_DESCARGADO","ip":"::ffff:181.23.113.245","endpoint":"/api/admin/backup-firmas","detalle":"Usuario: admin","ts":"2026-03-26T03:11:16.303Z"}]